ifccsv.py
ifccsv-0.8.3.dist-info/METADATA
ifccsv-0.8.3.dist-info/WHEEL
ifccsv-0.8.3.dist-info/top_level.txt
ifccsv-0.8.3.dist-info/RECORD
